[null,{"name":"pomoc","permissions":"NONE","restriction":"1","_id":"yFtYj","actions":[{"member":"1","varName":"","info":"2","storage":"1","varName2":"user","name":"Store Member Info"},{"member":"1","varName":"","info":"16","storage":"1","varName2":"avatar","name":"Store Member Info"},{"title":"","author":"${tempVars(\"user\")}","color":"","timestamp":"false","url":"","authorIcon":"${tempVars(\"avatar\")}","imageUrl":"","thumbUrl":"","storage":"1","varName":"embed","name":"Create Embed Message"},{"storage":"1","varName":"embed","message":"${member} Lista komend zostaa wysana na wiadomos prywatn.","name":"Set Embed Description"},{"storage":"1","varName":"embed","channel":"0","varName2":"","name":"Send Embed Message"},{"title":"**Oto moje komendy:**","author":"${tempVars(\"user\")}","color":"","timestamp":"false","url":"","authorIcon":"${tempVars(\"avatar\")}","imageUrl":"","thumbUrl":"","storage":"1","varName":"embed","name":"Create Embed Message"},{"storage":"1","varName":"embed","message":"**d!graj <tytul piosenki> -gram dany utwor.**\n**d!kolejka -pokazuj pi w utwor贸w kt贸re s w kolejce.**\n**d!glosnosc <liczba> -podgaszam lub przyciszam utw贸r.**\n**d!wyjdz -wychodz z kanalu glosowego.**\n**d!skip -skipuje jeden utw贸r.**\n**d!stop -zatrzymuje utw贸r.**","name":"Set Embed Description"},{"storage":"1","varName":"embed","channel":"1","varName2":"","varName3":"","storage3":"0","name":"Send Embed Message MOD"}]},{"name":"wejdz","permissions":"NONE","restriction":"1","_id":"lVPCM","actions":[{"member":"1","varName":"","info":"4","varName2":"","iftrue":"2","iftrueVal":"4","iffalse":"2","iffalseVal":"2","name":"Check If Member"},{"channel":"0","varName":"","message":"${member} Najpierw docz na kana gosowy! Co ja mam sam do siebie puszcza muzyk?","storage":"0","varName2":"","iffalse":"0","iffalseVal":"","name":"Send Message"},{"name":"End Action Sequence"},{"channel":"0","varName":"","name":"Join Voice Channel"}]},{"name":"graj","permissions":"NONE","restriction":"1","_id":"dfaXI","actions":[{"info":"1","infoIndex":"1","storage":"1","varName":"search","name":"Store Command Params"},{"server":"0","varName":"","storage":"1","varName2":"botmem","name":"Get Bot as Member"},{"member":"2","varName":"botmem","permission":"CONNECT","iftrue":"0","iftrueVal":"","iffalse":"2","iffalseVal":"22","name":"Check Member Permissions"},{"member":"2","varName":"botmem","permission":"SPEAK","iftrue":"0","iftrueVal":"","iffalse":"2","iffalseVal":"24","name":"Check Member Permissions"},{"member":"2","varName":"botmem","permission":"USE_VAD","iftrue":"0","iftrueVal":"","iffalse":"2","iffalseVal":"26","name":"Check Member Permissions"},{"video":"${tempVars(\"search\")}","key":"AIzaSyD5ch4JpCpBBoGdtCbpSVT5aUS6cHCFgpw","info":"6","resultNo":"0","storage":"1","varName":"videokind","name":"YouTube Search"},{"storage":"1","varName":"videokind","comparison":"1","value":"\"youtube#video\"","iftrue":"0","iftrueVal":"","iffalse":"2","iffalseVal":"28","name":"Check Variable"},{"token":"","user":"","pass":"","url":"https://www.googleapis.com/youtube/v3/search?part=snippet&maxResults=5&q=${tempVars(\"search\")}&key=AIzaSyD5ch4JpCpBBoGdtCbpSVT5aUS6cHCFgpw","path":"items[0].snippet.channelTitle","storage":"2","varName":"channel","debugMode":"1","headers":"","name":"Store Json From WebAPI"},{"token":"","user":"","pass":"","url":"https://www.googleapis.com/youtube/v3/search?part=snippet&maxResults=5&q=${tempVars(\"search\")}&key=AIzaSyD5ch4JpCpBBoGdtCbpSVT5aUS6cHCFgpw","path":"items[0].snippet.publishedAt","storage":"2","varName":"published","debugMode":"1","headers":"","name":"Store Json From WebAPI"},{"token":"","user":"","pass":"","url":"https://www.googleapis.com/youtube/v3/search?part=snippet&maxResults=5&q=${tempVars(\"search\")}&key=AIzaSyD5ch4JpCpBBoGdtCbpSVT5aUS6cHCFgpw","path":"items[0].snippet.thumbnails.default.url","storage":"2","varName":"coverart","debugMode":"1","headers":"","name":"Store Json From WebAPI"},{"token":"","user":"","pass":"","url":"https://www.googleapis.com/youtube/v3/search?part=snippet&maxResults=5&q=${tempVars(\"search\")}&key=AIzaSyD5ch4JpCpBBoGdtCbpSVT5aUS6cHCFgpw","path":"items[0].snippet.title","storage":"2","varName":"title","debugMode":"1","headers":"","name":"Store Json From WebAPI"},{"token":"","user":"","pass":"","url":"https://www.googleapis.com/youtube/v3/search?part=snippet&maxResults=5&q=${tempVars(\"search\")}&key=AIzaSyD5ch4JpCpBBoGdtCbpSVT5aUS6cHCFgpw","path":"items[0].id.videoId","storage":"2","varName":"url","debugMode":"1","headers":"","name":"Store Json From WebAPI"},{"channel":"0","varName":"","info":"2","storage":"1","varName2":"playchannel","name":"Store Voice Channel Info"},{"title":":arrow_forward: Dodano do kolejki: ${serverVars(\"title\")}","author":"","color":"e2e2e2","timestamp":"true","url":"https://www.youtube.com/watch?v=${serverVars(\"url\")}","authorIcon":"","imageUrl":"","thumbUrl":"${serverVars(\"coverart\")}","storage":"1","varName":"embed","name":"Create Embed Message"},{"storage":"1","varName":"embed","message":"Dadane przez: ${member.user.username}","footerIcon":"${member.user.avatarURL}","name":"Set Embed Footer"},{"time":"${serverVars(\"published\")}","storage":"2","varName":"realpublished","name":"Convert Timestamp to Date"},{"storage":"1","varName":"embed","fieldName":"Na kanale:","message":"${tempVars(\"playchannel\")}","inline":"0","name":"Add Embed Field"},{"storage":"1","varName":"embed","fieldName":"Opublikowano:","message":"${serverVars(\"realpublished\")}","inline":"0","name":"Add Embed Field"},{"storage":"1","varName":"embed","channel":"0","varName2":"","name":"Send Embed Message"},{"url":"${serverVars(\"url\")}","seek":"0","volume":"","passes":"1","bitrate":"64000","type":"0","name":"Play YouTube Video"},{"name":"End Action Sequence"},{"channel":"0","varName":"","message":":x: Bot nie ma pozwolenia na doczenie do Twojego kanau gosowego!","storage":"0","varName2":"","name":"Send Message"},{"name":"End Action Sequence"},{"channel":"0","varName":"","message":":x: Bot nie ma uprawnie do m贸wienia na tym  kanale gosowym!","storage":"0","varName2":"","name":"Send Message"},{"name":"End Action Sequence"},{"channel":"0","varName":"","message":":x: Bot nie ma uprawnie do korzystania z wykrywania aktywacji gosowej na tym kanale gosowym!","storage":"0","varName2":"","name":"Send Message"},{"name":"End Action Sequence"},{"channel":"0","varName":"","message":":x:Pr贸bujesz odtworzy kana lub playlist! Kanay to obiekty statyczne, a listy odtwarzania s obecnie nieobsugiwane! Wprowad藕 inne sowa kluczowe!","storage":"0","varName2":"","name":"Send Message"}],"comType":"0"},{"name":"stop","permissions":"NONE","restriction":"1","_id":"ybFMy","actions":[{"action":"1","name":"Control Audio"},{"channel":"0","varName":"","message":"${member} tw贸j utw贸r zosta zatrzymany. Aby go wznowi wpisz `d!resume`.","storage":"0","varName2":"","name":"Send Message"}]},{"name":"skip","permissions":"NONE","restriction":"1","_id":"hwdfH","actions":[{"amount":"1","name":"Skip Queue"},{"channel":"0","varName":"","message":"${member} Tw贸j utw贸r zosta skipnity.","storage":"0","varName2":"","name":"Send Message"}]},{"name":"glosnosc","permissions":"NONE","restriction":"1","_id":"zOcKc","actions":[{"info":"0","infoIndex":"1","storage":"1","varName":"nr","name":"Store Command Params"},{"FirstNumber":"${tempVars(\"nr\")}","info":"0","SecondNumber":"0","storage":"1","varName":"nr","name":"Basic Math Operation"},{"storage":"1","varName":"nr","comparison":"0","iftrue":"3","iftrueVal":"2","iffalse":"0","iffalseVal":"","name":"Check Variable Type"},{"channel":"0","varName":"","message":":x: Wprowad藕 numer. [1-100]","storage":"0","varName2":"","name":"Send Message"},{"name":"End Action Sequence"},{"storage":"1","varName":"nr","comparison":"3","value":"101","iftrue":"0","iftrueVal":"3","iffalse":"2","iffalseVal":"7","name":"Check Variable"},{"storage":"1","varName":"nr","comparison":"4","value":"0","iftrue":"0","iftrueVal":"2","iffalse":"2","iffalseVal":"7","name":"Check Variable"},{"volume":"${tempVars(\"nr\")}","name":"Set Audio Volume"},{"title":" gono bota ustawiona na ${tempVars(\"nr\")}!","author":"","color":"","timestamp":"false","url":"","authorIcon":"","imageUrl":"","thumbUrl":"","storage":"1","varName":"embed","name":"Create Embed Message"},{"storage":"1","varName":"embed","channel":"0","varName2":"","storage3":"0","varName3":"","name":"Send Embed Message"}]},{"name":"kolejka","permissions":"NONE","restriction":"1","_id":"qmTsw","actions":[{"title":"Aktualna lista kolejki:","author":"","color":"e2e2e2","timestamp":"true","url":"","authorIcon":"","imageUrl":"","thumbUrl":"","storage":"1","varName":"embed","name":"Create Embed Message"},{"server":"0","info":"4","storage":"1","varName":"nexturl","varName2":"","name":"Store Audio Info"},{"server":"0","info":"3","storage":"1","varName":"queuelist","varName2":"","name":"Store Audio Info"},{"slice":"${tempVars(\"queuelist\")}","startingNumber":"0","sliceLength":"11","storage":"1","varName":"slice1","name":"Slice"},{"slice":"${tempVars(\"queuelist\")}","startingNumber":"12","sliceLength":"11","storage":"1","varName":"slice2","name":"Slice"},{"slice":"${tempVars(\"queuelist\")}","startingNumber":"24","sliceLength":"11","storage":"1","varName":"slice3","name":"Slice"},{"slice":"${tempVars(\"queuelist\")}","startingNumber":"36","sliceLength":"11","storage":"1","varName":"slice4","name":"Slice"},{"slice":"${tempVars(\"queuelist\")}","startingNumber":"48","sliceLength":"11","storage":"1","varName":"slice5","name":"Slice"},{"server":"0","info":"5","storage":"1","varName":"queuelength","varName2":"","name":"Store Audio Info"},{"storage":"1","varName":"queuelength","comparison":"1","value":"1","iftrue":"0","iftrueVal":"","iffalse":"2","iffalseVal":"15","name":"Check Variable"},{"video":"https://youtube.com/watch?v=${tempVars(\"slice1\")}","key":"AIzaSyD5ch4JpCpBBoGdtCbpSVT5aUS6cHCFgpw","info":"1","resultNo":"0","storage":"1","varName":"videoname1","name":"YouTube Search"},{"storage":"1","varName":"embed","message":"`1.` **${tempVars(\"videoname1\")}**\n\n**Nastpny utw贸r w kolejce:**\n${tempVars(\"videoname1\")}\n\n**czna dugo kolejki:**\n${tempVars(\"queuelength\")}","name":"Set Embed Description"},{"storage":"1","varName":"embed","channel":"0","varName2":"","name":"Send Embed Message"},{"name":"End Action Sequence"},{"storage":"1","varName":"queuelength","comparison":"1","value":"2","iftrue":"0","iftrueVal":"","iffalse":"2","iffalseVal":"21","name":"Check Variable"},{"video":"https://youtube.com/watch?v=${tempVars(\"slice1\")}","key":"AIzaSyD5ch4JpCpBBoGdtCbpSVT5aUS6cHCFgpw","info":"1","resultNo":"0","storage":"1","varName":"videoname1","name":"YouTube Search"},{"video":"https://youtube.com/watch?v=${tempVars(\"slice2\")}","key":"AIzaSyD5ch4JpCpBBoGdtCbpSVT5aUS6cHCFgpw","info":"1","resultNo":"0","storage":"1","varName":"videoname2","name":"YouTube Search"},{"storage":"1","varName":"embed","message":"`1.` **${tempVars(\"videoname1\")}**\n`2.` **${tempVars(\"videoname2\")}**\n\n**Nastpny utw贸r w kolejce:**\n${tempVars(\"videoname1\")}\n\n**czna dugo kolejki:**\n${tempVars(\"queuelength\")}","name":"Set Embed Description"},{"storage":"1","varName":"embed","channel":"0","varName2":"","name":"Send Embed Message"},{"name":"End Action Sequence"},{"storage":"1","varName":"queuelength","comparison":"1","value":"3","iftrue":"0","iftrueVal":"","iffalse":"2","iffalseVal":"28","name":"Check Variable"},{"video":"https://youtube.com/watch?v=${tempVars(\"slice1\")}","key":"AIzaSyD5ch4JpCpBBoGdtCbpSVT5aUS6cHCFgpw","info":"1","resultNo":"0","storage":"1","varName":"videoname1","name":"YouTube Search"},{"video":"https://youtube.com/watch?v=${tempVars(\"slice2\")}","key":"AIzaSyD5ch4JpCpBBoGdtCbpSVT5aUS6cHCFgpw","info":"1","resultNo":"0","storage":"1","varName":"videoname2","name":"YouTube Search"},{"video":"https://youtube.com/watch?v=${tempVars(\"slice3\")}","key":"AIzaSyD5ch4JpCpBBoGdtCbpSVT5aUS6cHCFgpw","info":"1","resultNo":"0","storage":"1","varName":"videoname3","name":"YouTube Search"},{"storage":"1","varName":"embed","message":"`1.` **${tempVars(\"videoname1\")}**\n`2.` **${tempVars(\"videoname2\")}**\n`3.` **${tempVars(\"videoname3\")}**\n\n**Nastpny utw贸r w kolejce:**\n${tempVars(\"videoname1\")}\n\n**czna dugo kolejki:**\n${tempVars(\"queuelength\")}","name":"Set Embed Description"},{"storage":"1","varName":"embed","channel":"0","varName2":"","name":"Send Embed Message"},{"name":"End Action Sequence"},{"storage":"1","varName":"queuelength","comparison":"1","value":"4","iftrue":"0","iftrueVal":"","iffalse":"2","iffalseVal":"36","name":"Check Variable"},{"video":"https://youtube.com/watch?v=${tempVars(\"slice1\")}","key":"AIzaSyD5ch4JpCpBBoGdtCbpSVT5aUS6cHCFgpw","info":"1","resultNo":"0","storage":"1","varName":"videoname1","name":"YouTube Search"},{"video":"https://youtube.com/watch?v=${tempVars(\"slice2\")}","key":"AIzaSyD5ch4JpCpBBoGdtCbpSVT5aUS6cHCFgpw","info":"1","resultNo":"0","storage":"1","varName":"videoname2","name":"YouTube Search"},{"video":"https://youtube.com/watch?v=${tempVars(\"slice3\")}","key":"AIzaSyD5ch4JpCpBBoGdtCbpSVT5aUS6cHCFgpw","info":"1","resultNo":"0","storage":"1","varName":"videoname3","name":"YouTube Search"},{"video":"https://youtube.com/watch?v=${tempVars(\"slice4\")}","key":"AIzaSyD5ch4JpCpBBoGdtCbpSVT5aUS6cHCFgpw","info":"1","resultNo":"0","storage":"1","varName":"videoname4","name":"YouTube Search"},{"storage":"1","varName":"embed","message":"`1.` **${tempVars(\"videoname1\")}**\n`2.` **${tempVars(\"videoname2\")}**\n`3.` **${tempVars(\"videoname3\")}**\n`4.` **${tempVars(\"videoname4\")}**\n\n**Nastpny utw贸r w kolejce:**\n${tempVars(\"videoname1\")}\n\n**czna dugo kolejki:**\n${tempVars(\"queuelength\")}","name":"Set Embed Description"},{"storage":"1","varName":"embed","channel":"0","varName2":"","name":"Send Embed Message"},{"name":"End Action Sequence"},{"storage":"1","varName":"queuelength","comparison":"4","value":"4","iftrue":"0","iftrueVal":"","iffalse":"2","iffalseVal":"45","name":"Check Variable"},{"video":"https://youtube.com/watch?v=${tempVars(\"slice1\")}","key":"AIzaSyD5ch4JpCpBBoGdtCbpSVT5aUS6cHCFgpw","info":"1","resultNo":"0","storage":"1","varName":"videoname1","name":"YouTube Search"},{"video":"https://youtube.com/watch?v=${tempVars(\"slice2\")}","key":"AIzaSyD5ch4JpCpBBoGdtCbpSVT5aUS6cHCFgpw","info":"1","resultNo":"0","storage":"1","varName":"videoname2","name":"YouTube Search"},{"video":"https://youtube.com/watch?v=${tempVars(\"slice3\")}","key":"AIzaSyD5ch4JpCpBBoGdtCbpSVT5aUS6cHCFgpw","info":"1","resultNo":"0","storage":"1","varName":"videoname3","name":"YouTube Search"},{"video":"https://youtube.com/watch?v=${tempVars(\"slice4\")}","key":"AIzaSyD5ch4JpCpBBoGdtCbpSVT5aUS6cHCFgpw","info":"1","resultNo":"0","storage":"1","varName":"videoname4","name":"YouTube Search"},{"video":"https://youtube.com/watch?v=${tempVars(\"slice5\")}","key":"AIzaSyD5ch4JpCpBBoGdtCbpSVT5aUS6cHCFgpw","info":"1","resultNo":"0","storage":"1","varName":"videoname5","name":"YouTube Search"},{"storage":"1","varName":"embed","message":"`1.` **${tempVars(\"videoname1\")}**\n`2.` **${tempVars(\"videoname2\")}**\n`3.` **${tempVars(\"videoname3\")}**\n`4.` **${tempVars(\"videoname4\")}**\n`5.` **${tempVars(\"videoname5\")}**\n\n**Nastpny utw贸r w kolejce:**\n${tempVars(\"videoname1\")}\n\n**czna dugo kolejki:**\n${tempVars(\"queuelength\")}","name":"Set Embed Description"},{"storage":"1","varName":"embed","channel":"0","varName2":"","name":"Send Embed Message"},{"name":"End Action Sequence"},{"title":"Bd!","author":"","color":"df4444","timestamp":"true","url":"","authorIcon":"","imageUrl":"","thumbUrl":"","storage":"1","varName":"embederr","name":"Create Embed Message"},{"storage":"1","varName":"embederr","message":"","name":"Set Embed Description"},{"storage":"1","varName":"embed","channel":"0","varName2":"","name":"Send Embed Message"}],"comType":"0"},{"name":"resume","permissions":"NONE","restriction":"1","_id":"GSUBF","actions":[{"action":"2","name":"Control Audio"},{"channel":"0","varName":"","message":"Okey ${member} tw贸j utw贸r zosta wznowiony.","storage":"0","varName2":"","iffalse":"0","iffalseVal":"","name":"Send Message"}]},{"name":"wyjdz","permissions":"NONE","restriction":"1","_id":"EqVIj","actions":[{"member":"1","varName":"","info":"4","varName2":"","iftrue":"0","iftrueVal":"","iffalse":"0","iffalseVal":"","name":"Check If Member"},{"name":"Leave Voice Channel"}]}]